{
    "漏洞标题": "北京神州视翰科技有限公司多媒体综合业务显示系统存在SQL注入漏洞（CNVD-2025-17836）",
    "CNVD-ID": "CNVD-2025-17836",
    "公开日期": "2025-08-07",
    "危害级别": "中",
    "影响产品": "北京神州视翰科技有限公司 多媒体综合业务显示系统",
    "漏洞描述": "北京神州视翰科技有限公司是一家深耕可视化领域的企业。\n北京神州视翰科技有限公司多媒体综合业务显示系统存在SQL注入漏洞，攻击者可利用该漏洞获取数据库敏感信息。",
    "漏洞类型": "通用型漏洞",
    "参考链接": "",
    "漏洞解决方案": "厂商已发布了漏洞修复程序，请及时关注更新：\nhttp://www.china-shine.com.cn/",
    "厂商补丁": "https://www.cnvd.org.cn/patchInfo/show/716791",
    "验证信息": "已验证",
    "报送时间": "2025-06-23",
    "收录时间": "2025-08-08",
    "更新时间": "2025-08-08",
    "漏洞附件": "附件暂不公开"
}