{
    "漏洞标题": "用友网络科技股份有限公司用友NC65存在SQL注入漏洞",
    "CNVD-ID": "CNVD-2025-13528",
    "公开日期": "2025-06-27",
    "危害级别": "高",
    "影响产品": "用友网络科技股份有限公司 用友NC 65\n用友网络科技股份有限公司 用友NC65",
    "漏洞描述": "用友NC65是面向中大型企业的集团级ERP系统\n用友网络科技股份有限公司用友NC65存在SQL注入漏洞，攻击者可利用该漏洞获取数据库敏感信息。",
    "漏洞类型": "通用型漏洞",
    "参考链接": "",
    "漏洞解决方案": "厂商已发布了漏洞修复程序，请及时关注更新： \nhttps://security.yonyou.com/#/noticeInfo?id=702",
    "厂商补丁": "https://www.cnvd.org.cn/patchInfo/show/702631",
    "验证信息": "已验证",
    "报送时间": "2025-05-20",
    "收录时间": "2025-06-26",
    "更新时间": "2025-06-27",
    "漏洞附件": "附件暂不公开"
}