{
    "漏洞标题": "中科新业网络哨兵存在通用任意文件上传漏洞",
    "CNVD-ID": "CNVD-2016-07062",
    "公开日期": "2025-04-20",
    "危害级别": "高",
    "影响产品": "深圳市中科新业信息科技发展有限公司 中科新业网络哨兵网络安全审计系统",
    "漏洞描述": "中科新业网络哨兵是互联网安全审计系统，集行为审计与内容审计为一体，以旁路的方式部署在网络出口。\n中科新业网络哨兵存在任意文件上传漏洞。攻击者可以利用漏洞上传php文件即可获取shell。",
    "漏洞类型": "通用型漏洞",
    "参考链接": "http://www.wooyun.org/bugs/wooyun-2015-0108640",
    "漏洞解决方案": "目前没有详细解决方案提供：\nhttp://www.seentech.com.cn/",
    "厂商补丁": "",
    "验证信息": "(暂无验证信息)",
    "报送时间": "2015-04-20",
    "收录时间": "2016-09-01",
    "更新时间": "2020-04-08",
    "漏洞附件": "(无附件)"
}